odoo8_addon_connector_redmine-8.0.2.0.0.99.dev2-py2.7-nspkg.pth
odoo8_addon_connector_redmine-8.0.2.0.0.99.dev2.dist-info/METADATA
odoo8_addon_connector_redmine-8.0.2.0.0.99.dev2.dist-info/RECORD
odoo8_addon_connector_redmine-8.0.2.0.0.99.dev2.dist-info/WHEEL
odoo8_addon_connector_redmine-8.0.2.0.0.99.dev2.dist-info/namespace_packages.txt
odoo8_addon_connector_redmine-8.0.2.0.0.99.dev2.dist-info/top_level.txt
odoo_addons/connector_redmine/README.rst
odoo_addons/connector_redmine/__init__.py
odoo_addons/connector_redmine/__openerp__.py
odoo_addons/connector_redmine/backend.py
odoo_addons/connector_redmine/connector.py
odoo_addons/connector_redmine/session.py
odoo_addons/connector_redmine/i18n/en.po
odoo_addons/connector_redmine/i18n/fr.po
odoo_addons/connector_redmine/migrations/8.0.2.0.0/post-migration.py
odoo_addons/connector_redmine/models/__init__.py
odoo_addons/connector_redmine/models/redmine_backend.py
odoo_addons/connector_redmine/models/redmine_binding.py
odoo_addons/connector_redmine/models/redmine_hr_analytic_timesheet.py
odoo_addons/connector_redmine/models/res_users.py
odoo_addons/connector_redmine/security/ir.model.access.csv
odoo_addons/connector_redmine/static/description/icon.png
odoo_addons/connector_redmine/static/src/img/icon.png
odoo_addons/connector_redmine/static/src/img/icon.svg
odoo_addons/connector_redmine/tests/__init__.py
odoo_addons/connector_redmine/tests/test_connector_redmine.py
odoo_addons/connector_redmine/unit/__init__.py
odoo_addons/connector_redmine/unit/backend_adapter.py
odoo_addons/connector_redmine/unit/binder.py
odoo_addons/connector_redmine/unit/import_synchronizer.py
odoo_addons/connector_redmine/unit/mapper.py
odoo_addons/connector_redmine/views/redmine_backend_view.xml
odoo_addons/connector_redmine/views/redmine_menu.xml
odoo_addons/connector_redmine/views/res_users.xml
